tardiff2/__init__.py
tardiff2/__main__.py
tardiff2/defs.py
tardiff2/opts.py
tardiff2/tardiff.py
tardiff2-0.1.1.dist-info/entry_points.txt
tardiff2-0.1.1.dist-info/licenses/LICENSE
tardiff2-0.1.1.dist-info/WHEEL
tardiff2-0.1.1.dist-info/METADATA
tardiff2-0.1.1.dist-info/RECORD
